README.md
setup.py
mpds_client/__init__.py
mpds_client/errors.py
mpds_client/export_MPDS.py
mpds_client/retrieve_MPDS.py
mpds_client/test_fields.py
mpds_client/test_pd.py
mpds_client/test_retrieve_MPDS.py
mpds_client.egg-info/PKG-INFO
mpds_client.egg-info/SOURCES.txt
mpds_client.egg-info/dependency_links.txt
mpds_client.egg-info/requires.txt
mpds_client.egg-info/top_level.txt