Metadata-Version: 1.1
Name: mpds-client
Version: 0.0.22
Summary: MPDS platform API client
Home-page: https://github.com/mpds-io/python-api-client
Author: Evgeny Blokhin
Author-email: eb@tilde.pro
License: MIT
Keywords: materials informatics crystal structures phase diagrams physical properties PAULING FILE MPDS platform API
Platform: UNKNOWN
Classifier: Development Status :: 3 - Alpha
Classifier: Intended Audience :: Science/Research
Classifier: Topic :: Scientific/Engineering :: Chemistry
Classifier: Topic :: Scientific/Engineering :: Physics
Classifier: Topic :: Scientific/Engineering :: Information Analysis
Classifier: Topic :: Software Development :: Libraries :: Python Modules
Classifier: License :: OSI Approved :: MIT License
Classifier: Programming Language :: Python :: 2
Classifier: Programming Language :: Python :: 2.7
Classifier: Programming Language :: Python :: 3
Classifier: Programming Language :: Python :: 3.5
Classifier: Programming Language :: Python :: 3.6
Classifier: Programming Language :: Python :: 3.7
Classifier: Programming Language :: Python :: 3.8
